setup.py
redis/__init__.py
redis/redis.py
redis/trace.py
redis_tornado.egg-info/PKG-INFO
redis_tornado.egg-info/SOURCES.txt
redis_tornado.egg-info/dependency_links.txt
redis_tornado.egg-info/requires.txt
redis_tornado.egg-info/top_level.txt