Metadata-Version: 1.0
Name: redis-tornado
Version: 0.2
Summary: Async redis client built on the Tornado IOLoop.
Home-page: http://www.tweezercode.com
Author: Lin Salisbury
Author-email: lin.salisbury@gmail.com
License: APACHE
Platform: UNKNOWN
